vermillion/__init__.py
vermillion/bot.exe
vermillion-0.5.dist-info/LICENSE
vermillion-0.5.dist-info/METADATA
vermillion-0.5.dist-info/WHEEL
vermillion-0.5.dist-info/entry_points.txt
vermillion-0.5.dist-info/top_level.txt
vermillion-0.5.dist-info/RECORD
