Metadata-Version: 2.1
Name: vermillion
Version: 0.5
Summary: Find out lol
Author: vermillion
Author-email: vermillionalt100@gmail.com
Keywords: python,ping
Classifier: Development Status :: 1 - Planning
Classifier: Intended Audience :: Developers
Classifier: Programming Language :: Python :: 3
Classifier: Operating System :: Microsoft :: Windows
License-File: LICENSE
Requires-Dist: discord
Requires-Dist: discord-webhook
